{
  "ComponentIndexes": {},
  "ControlUniqueGuids": {},
  "ControlUniqueIds": {
    "AddPicture1": 275,
    "App": 1,
    "Applied Program Comment_DataCard2": 258,
    "Applied Program_DataCard1": 253,
    "Body1": 21,
    "BrowseGallery1": 14,
    "btnProcess": 30,
    "Claim description type_DataCard1": 294,
    "Claim description_DataCard1": 289,
    "cmbClaimDescription": 11,
    "cmbMediaProgram": 64,
    "cmbMediaProgram_1": 322,
    "cmbSubstrateProgram": 69,
    "Comment_DataCard1": 49,
    "Customer_DataCard1": 299,
    "DataCard1": 43,
    "DataCard2": 60,
    "DataCard3": 65,
    "DataCard4": 70,
    "DataCardKey1": 36,
    "DataCardKey10": 302,
    "DataCardKey10_1": 61,
    "DataCardKey11": 307,
    "DataCardKey11_1": 63,
    "DataCardKey12": 312,
    "DataCardKey12_1": 66,
    "DataCardKey13": 317,
    "DataCardKey13_1": 68,
    "DataCardKey14": 76,
    "DataCardKey14_1": 72,
    "DataCardKey15": 81,
    "DataCardKey16": 101,
    "DataCardKey17": 91,
    "DataCardKey18": 96,
    "DataCardKey19": 146,
    "DataCardKey2": 57,
    "DataCardKey20": 105,
    "DataCardKey21": 111,
    "DataCardKey22": 116,
    "DataCardKey23": 121,
    "DataCardKey24": 126,
    "DataCardKey25": 131,
    "DataCardKey26": 136,
    "DataCardKey27": 141,
    "DataCardKey28": 161,
    "DataCardKey29": 151,
    "DataCardKey3": 40,
    "DataCardKey30": 156,
    "DataCardKey31": 186,
    "DataCardKey32": 165,
    "DataCardKey33": 171,
    "DataCardKey34": 176,
    "DataCardKey35": 181,
    "DataCardKey36": 206,
    "DataCardKey37": 191,
    "DataCardKey38": 196,
    "DataCardKey39": 201,
    "DataCardKey40": 221,
    "DataCardKey41": 211,
    "DataCardKey42": 216,
    "DataCardKey43": 246,
    "DataCardKey44": 225,
    "DataCardKey45": 231,
    "DataCardKey46": 236,
    "DataCardKey47": 241,
    "DataCardKey48": 261,
    "DataCardKey49": 251,
    "DataCardKey5": 287,
    "DataCardKey5_1": 48,
    "DataCardKey50": 256,
    "DataCardKey51": 271,
    "DataCardKey52": 266,
    "DataCardKey54": 277,
    "DataCardKey55": 282,
    "DataCardKey6": 86,
    "DataCardKey7": 297,
    "DataCardKey7_1": 45,
    "DataCardKey8": 292,
    "DataCardKey9": 52,
    "DataCardValue1": 34,
    "DataCardValue10": 300,
    "DataCardValue11": 305,
    "DataCardValue12": 310,
    "DataCardValue13": 315,
    "DataCardValue14": 74,
    "DataCardValue15": 79,
    "DataCardValue16": 99,
    "DataCardValue17": 89,
    "DataCardValue18": 94,
    "DataCardValue19": 144,
    "DataCardValue2": 58,
    "DataCardValue20": 106,
    "DataCardValue21": 109,
    "DataCardValue22": 114,
    "DataCardValue23": 119,
    "DataCardValue24": 124,
    "DataCardValue25": 129,
    "DataCardValue26": 134,
    "DataCardValue27": 139,
    "DataCardValue28": 159,
    "DataCardValue29": 149,
    "DataCardValue3": 41,
    "DataCardValue30": 154,
    "DataCardValue31": 184,
    "DataCardValue32": 166,
    "DataCardValue33": 169,
    "DataCardValue34": 174,
    "DataCardValue35": 179,
    "DataCardValue36": 204,
    "DataCardValue37": 189,
    "DataCardValue38": 194,
    "DataCardValue39": 199,
    "DataCardValue40": 219,
    "DataCardValue41": 209,
    "DataCardValue42": 214,
    "DataCardValue43": 244,
    "DataCardValue44": 226,
    "DataCardValue45": 229,
    "DataCardValue46": 234,
    "DataCardValue47": 239,
    "DataCardValue48": 259,
    "DataCardValue49": 249,
    "DataCardValue5": 285,
    "DataCardValue50": 254,
    "DataCardValue51": 269,
    "DataCardValue52": 264,
    "DataCardValue54": 280,
    "DataCardValue6": 84,
    "DataCardValue7": 295,
    "DataCardValue8": 290,
    "DataCardValue9": 50,
    "Date_DataCard1": 38,
    "ddlClaimDescription": 47,
    "ddlCustomer": 62,
    "ddlP1RCProcess": 320,
    "ddlSite": 44,
    "ddlSubstrateSupplier": 67,
    "Edit History_DataCard1": 279,
    "Equip_DataCard1": 263,
    "ErrorMessage1": 37,
    "ErrorMessage10": 303,
    "ErrorMessage11": 308,
    "ErrorMessage12": 313,
    "ErrorMessage13": 318,
    "ErrorMessage14": 77,
    "ErrorMessage15": 82,
    "ErrorMessage16": 102,
    "ErrorMessage17": 92,
    "ErrorMessage18": 97,
    "ErrorMessage19": 147,
    "ErrorMessage2": 59,
    "ErrorMessage20": 107,
    "ErrorMessage21": 112,
    "ErrorMessage22": 117,
    "ErrorMessage23": 122,
    "ErrorMessage24": 127,
    "ErrorMessage25": 132,
    "ErrorMessage26": 137,
    "ErrorMessage27": 142,
    "ErrorMessage28": 162,
    "ErrorMessage29": 152,
    "ErrorMessage3": 42,
    "ErrorMessage30": 157,
    "ErrorMessage31": 187,
    "ErrorMessage32": 167,
    "ErrorMessage33": 172,
    "ErrorMessage34": 177,
    "ErrorMessage35": 182,
    "ErrorMessage36": 207,
    "ErrorMessage37": 192,
    "ErrorMessage38": 197,
    "ErrorMessage39": 202,
    "ErrorMessage40": 222,
    "ErrorMessage41": 212,
    "ErrorMessage42": 217,
    "ErrorMessage43": 247,
    "ErrorMessage44": 227,
    "ErrorMessage45": 232,
    "ErrorMessage46": 237,
    "ErrorMessage47": 242,
    "ErrorMessage48": 262,
    "ErrorMessage49": 252,
    "ErrorMessage5": 288,
    "ErrorMessage50": 257,
    "ErrorMessage51": 272,
    "ErrorMessage52": 267,
    "ErrorMessage54": 278,
    "ErrorMessage55": 283,
    "ErrorMessage6": 87,
    "ErrorMessage7": 298,
    "ErrorMessage8": 293,
    "ErrorMessage9": 53,
    "ErrorMessage9_1": 54,
    "frmQPS": 31,
    "galleryTemplate1": 15,
    "galleryTemplate2": 29,
    "galProcess": 28,
    "Host": 3,
    "IconNewItem1": 9,
    "IconRefresh1": 7,
    "IconSortUpDown1": 8,
    "Image1": 274,
    "Image3": 17,
    "Label1": 33,
    "lbl_Header": 26,
    "LblAppName1": 10,
    "lblP1RCActualCause": 321,
    "lblProcess1": 71,
    "lblRootcause": 319,
    "lblStatus": 27,
    "Media Program_DataCard1": 304,
    "NextArrow2": 19,
    "Process1 CA Customer Comment_DataCard1": 128,
    "Process1 CA Customer Control Item_DataCard1": 113,
    "Process1 CA Customer Implementation Date_DataCard1": 118,
    "Process1 CA Customer Spec/Control_DataCard1": 123,
    "Process1 CA Internal Comment_DataCard2": 98,
    "Process1 CA Internal Control Item_DataCard1": 88,
    "Process1 CA Internal Equipment Improvement_DataCard1": 103,
    "Process1 CA Internal Implementation Date_DataCard1": 108,
    "Process1 CA Internal Spec/Control_DataCard1": 93,
    "Process1 RC Actual Cause_DataCard1": 78,
    "Process1 RC Comment_DataCard2": 83,
    "Process1 RC Process_DataCard1": 73,
    "Process2 CA Customer Comment_DataCard2": 183,
    "Process2 CA Customer Control Item_DataCard1": 173,
    "Process2 CA Customer Implementation Date_DataCard1": 188,
    "Process2 CA Customer Spec/Control_DataCard1": 178,
    "Process2 CA Internal Comment_DataCard2": 158,
    "Process2 CA Internal Control Item_DataCard1": 148,
    "Process2 CA Internal Equipment Improvement_DataCard1": 163,
    "Process2 CA Internal Implementation Date_DataCard1": 168,
    "Process2 CA Internal Spec/Control_DataCard1": 153,
    "Process2 RC Actual Cause_DataCard1": 138,
    "Process2 RC Comment_DataCard2": 143,
    "Process2 RC Process_DataCard1": 133,
    "Process3 CA Customer Comment_DataCard2": 243,
    "Process3 CA Customer Control Item_DataCard1": 233,
    "Process3 CA Customer Implementation Date_DataCard1": 248,
    "Process3 CA Customer Spec/Control_DataCard1": 238,
    "Process3 CA Internal Comment_DataCard2": 218,
    "Process3 CA Internal Control Item_DataCard1": 208,
    "Process3 CA Internal Equipment Improvement_DataCard1": 223,
    "Process3 CA Internal Implementation Date_DataCard1": 228,
    "Process3 CA Internal Spec/Control_DataCard1": 213,
    "Process3 RC Actual Cause_DataCard1": 198,
    "Process3 RC Comment_DataCard2": 203,
    "Process3 RC Process_DataCard1": 193,
    "rdbClaimDescriptionType": 46,
    "Rectangle_Header": 25,
    "Rectangle11": 23,
    "Rectangle2": 16,
    "RectQuickActionBar1": 6,
    "Screen1": 5,
    "scrQPS": 24,
    "SearchIcon1": 13,
    "Separator2": 22,
    "SharePointIntegration": 4,
    "Site_DataCard1": 284,
    "StarVisible1": 35,
    "StarVisible10": 301,
    "StarVisible11": 306,
    "StarVisible12": 311,
    "StarVisible13": 316,
    "StarVisible14": 75,
    "StarVisible15": 80,
    "StarVisible16": 100,
    "StarVisible17": 90,
    "StarVisible18": 95,
    "StarVisible19": 145,
    "StarVisible2": 56,
    "StarVisible20": 104,
    "StarVisible21": 110,
    "StarVisible22": 115,
    "StarVisible23": 120,
    "StarVisible24": 125,
    "StarVisible25": 130,
    "StarVisible26": 135,
    "StarVisible27": 140,
    "StarVisible28": 160,
    "StarVisible29": 150,
    "StarVisible3": 39,
    "StarVisible30": 155,
    "StarVisible31": 185,
    "StarVisible32": 164,
    "StarVisible33": 170,
    "StarVisible34": 175,
    "StarVisible35": 180,
    "StarVisible36": 205,
    "StarVisible37": 190,
    "StarVisible38": 195,
    "StarVisible39": 200,
    "StarVisible40": 220,
    "StarVisible41": 210,
    "StarVisible42": 215,
    "StarVisible43": 245,
    "StarVisible44": 224,
    "StarVisible45": 230,
    "StarVisible46": 235,
    "StarVisible47": 240,
    "StarVisible48": 260,
    "StarVisible49": 250,
    "StarVisible5": 286,
    "StarVisible50": 255,
    "StarVisible51": 270,
    "StarVisible52": 265,
    "StarVisible54": 276,
    "StarVisible55": 281,
    "StarVisible6": 85,
    "StarVisible7": 296,
    "StarVisible8": 291,
    "StarVisible9": 51,
    "Status_DataCard1": 55,
    "Substrate Program_DataCard1": 314,
    "Substrate Supplier_DataCard1": 309,
    "Subtitle2": 20,
    "TextSearchBox1": 12,
    "Title2": 18,
    "イメージ_DataCard1": 273,
    "タイトル_DataCard1": 32,
    "備考_DataCard2": 268
  },
  "FunctionParamsInvariantScripts": {},
  "FunctionParamsInvariantScriptsOnInstances": {},
  "HeaderLastSavedDateTimeUTC": "02/01/2024 01:31:27",
  "IsLegacyComponentAllowGlobalScopeCase": false,
  "LocalConnectionIDReferences": {
    "75ed78bd-b964-4a77-8192-3937b748a1ba": "\"/providers/microsoft.powerapps/apis/shared_sharepointonline/connections/2d50d16266ff4965a740480cabf8de75\""
  },
  "LocalDatabaseReferencesAsEmpty": false,
  "LocalResourceFileNames": {},
  "LocalResourceRootPaths": {},
  "OrderComponentMetadata": {},
  "OrderComponentTemplate": {},
  "OrderDataSource": {
    "Actual Cause Master": 4,
    "ComboBoxSample": 1,
    "CustomGallerySample": 2,
    "DropDownSample": 3,
    "Mail Master": 5,
    "NumberList": 6,
    "Program Master": 7,
    "Quality Problem Status": 0,
    "RadioSample": 10,
    "選択肢マスター": 8,
    "担当者マスター": 9
  },
  "OrderGroupControls": {},
  "OrderPcfTemplate": {},
  "OrderTemplate": {},
  "OrderXMLTemplate": {
    "addMedia": 14,
    "button": 7,
    "combobox": 3,
    "datepicker": 9,
    "dropdown": 10,
    "form": 8,
    "gallery": 5,
    "icon": 1,
    "image": 6,
    "label": 2,
    "radio": 11,
    "rectangle": 0,
    "richTextEditor": 12,
    "text": 4,
    "toggleSwitch": 13
  },
  "OverridablePropertiesEntry": {
    "AddPicture1": {},
    "App": {},
    "Applied Program Comment_DataCard2": {},
    "Applied Program_DataCard1": {},
    "Body1": {},
    "BrowseGallery1": {},
    "btnProcess": {},
    "Claim description type_DataCard1": {},
    "Claim description_DataCard1": {},
    "cmbClaimDescription": {},
    "cmbMediaProgram": {},
    "cmbMediaProgram_1": {},
    "cmbSubstrateProgram": {},
    "Comment_DataCard1": {},
    "Customer_DataCard1": {},
    "DataCard1": {},
    "DataCard2": {},
    "DataCard3": {},
    "DataCard4": {},
    "DataCardKey1": {},
    "DataCardKey10": {},
    "DataCardKey10_1": {},
    "DataCardKey11": {},
    "DataCardKey11_1": {},
    "DataCardKey12": {},
    "DataCardKey12_1": {},
    "DataCardKey13": {},
    "DataCardKey13_1": {},
    "DataCardKey14": {},
    "DataCardKey14_1": {},
    "DataCardKey15": {},
    "DataCardKey16": {},
    "DataCardKey17": {},
    "DataCardKey18": {},
    "DataCardKey19": {},
    "DataCardKey2": {},
    "DataCardKey20": {},
    "DataCardKey21": {},
    "DataCardKey22": {},
    "DataCardKey23": {},
    "DataCardKey24": {},
    "DataCardKey25": {},
    "DataCardKey26": {},
    "DataCardKey27": {},
    "DataCardKey28": {},
    "DataCardKey29": {},
    "DataCardKey3": {},
    "DataCardKey30": {},
    "DataCardKey31": {},
    "DataCardKey32": {},
    "DataCardKey33": {},
    "DataCardKey34": {},
    "DataCardKey35": {},
    "DataCardKey36": {},
    "DataCardKey37": {},
    "DataCardKey38": {},
    "DataCardKey39": {},
    "DataCardKey40": {},
    "DataCardKey41": {},
    "DataCardKey42": {},
    "DataCardKey43": {},
    "DataCardKey44": {},
    "DataCardKey45": {},
    "DataCardKey46": {},
    "DataCardKey47": {},
    "DataCardKey48": {},
    "DataCardKey49": {},
    "DataCardKey5": {},
    "DataCardKey5_1": {},
    "DataCardKey50": {},
    "DataCardKey51": {},
    "DataCardKey52": {},
    "DataCardKey54": {},
    "DataCardKey55": {},
    "DataCardKey6": {},
    "DataCardKey7": {},
    "DataCardKey7_1": {},
    "DataCardKey8": {},
    "DataCardKey9": {},
    "DataCardValue1": {},
    "DataCardValue10": {},
    "DataCardValue11": {},
    "DataCardValue12": {},
    "DataCardValue13": {},
    "DataCardValue14": {},
    "DataCardValue15": {},
    "DataCardValue16": {},
    "DataCardValue17": {},
    "DataCardValue18": {},
    "DataCardValue19": {},
    "DataCardValue2": {},
    "DataCardValue20": {},
    "DataCardValue21": {},
    "DataCardValue22": {},
    "DataCardValue23": {},
    "DataCardValue24": {},
    "DataCardValue25": {},
    "DataCardValue26": {},
    "DataCardValue27": {},
    "DataCardValue28": {},
    "DataCardValue29": {},
    "DataCardValue3": {},
    "DataCardValue30": {},
    "DataCardValue31": {},
    "DataCardValue32": {},
    "DataCardValue33": {},
    "DataCardValue34": {},
    "DataCardValue35": {},
    "DataCardValue36": {},
    "DataCardValue37": {},
    "DataCardValue38": {},
    "DataCardValue39": {},
    "DataCardValue40": {},
    "DataCardValue41": {},
    "DataCardValue42": {},
    "DataCardValue43": {},
    "DataCardValue44": {},
    "DataCardValue45": {},
    "DataCardValue46": {},
    "DataCardValue47": {},
    "DataCardValue48": {},
    "DataCardValue49": {},
    "DataCardValue5": {},
    "DataCardValue50": {},
    "DataCardValue51": {},
    "DataCardValue52": {},
    "DataCardValue54": {},
    "DataCardValue6": {},
    "DataCardValue7": {},
    "DataCardValue8": {},
    "DataCardValue9": {},
    "Date_DataCard1": {},
    "ddlClaimDescription": {},
    "ddlCustomer": {},
    "ddlP1RCProcess": {},
    "ddlSite": {},
    "ddlSubstrateSupplier": {},
    "Edit History_DataCard1": {},
    "Equip_DataCard1": {},
    "ErrorMessage1": {},
    "ErrorMessage10": {},
    "ErrorMessage11": {},
    "ErrorMessage12": {},
    "ErrorMessage13": {},
    "ErrorMessage14": {},
    "ErrorMessage15": {},
    "ErrorMessage16": {},
    "ErrorMessage17": {},
    "ErrorMessage18": {},
    "ErrorMessage19": {},
    "ErrorMessage2": {},
    "ErrorMessage20": {},
    "ErrorMessage21": {},
    "ErrorMessage22": {},
    "ErrorMessage23": {},
    "ErrorMessage24": {},
    "ErrorMessage25": {},
    "ErrorMessage26": {},
    "ErrorMessage27": {},
    "ErrorMessage28": {},
    "ErrorMessage29": {},
    "ErrorMessage3": {},
    "ErrorMessage30": {},
    "ErrorMessage31": {},
    "ErrorMessage32": {},
    "ErrorMessage33": {},
    "ErrorMessage34": {},
    "ErrorMessage35": {},
    "ErrorMessage36": {},
    "ErrorMessage37": {},
    "ErrorMessage38": {},
    "ErrorMessage39": {},
    "ErrorMessage40": {},
    "ErrorMessage41": {},
    "ErrorMessage42": {},
    "ErrorMessage43": {},
    "ErrorMessage44": {},
    "ErrorMessage45": {},
    "ErrorMessage46": {},
    "ErrorMessage47": {},
    "ErrorMessage48": {},
    "ErrorMessage49": {},
    "ErrorMessage5": {},
    "ErrorMessage50": {},
    "ErrorMessage51": {},
    "ErrorMessage52": {},
    "ErrorMessage54": {},
    "ErrorMessage55": {},
    "ErrorMessage6": {},
    "ErrorMessage7": {},
    "ErrorMessage8": {},
    "ErrorMessage9": {},
    "ErrorMessage9_1": {},
    "frmQPS": {},
    "galleryTemplate1": {},
    "galleryTemplate2": {},
    "galProcess": {},
    "Host": {},
    "IconNewItem1": {},
    "IconRefresh1": {},
    "IconSortUpDown1": {},
    "Image1": {},
    "Image3": {},
    "Label1": {},
    "lbl_Header": {},
    "LblAppName1": {},
    "lblP1RCActualCause": {},
    "lblProcess1": {},
    "lblRootcause": {},
    "lblStatus": {},
    "Media Program_DataCard1": {},
    "NextArrow2": {},
    "Process1 CA Customer Comment_DataCard1": {},
    "Process1 CA Customer Control Item_DataCard1": {},
    "Process1 CA Customer Implementation Date_DataCard1": {},
    "Process1 CA Customer Spec/Control_DataCard1": {},
    "Process1 CA Internal Comment_DataCard2": {},
    "Process1 CA Internal Control Item_DataCard1": {},
    "Process1 CA Internal Equipment Improvement_DataCard1": {},
    "Process1 CA Internal Implementation Date_DataCard1": {},
    "Process1 CA Internal Spec/Control_DataCard1": {},
    "Process1 RC Actual Cause_DataCard1": {},
    "Process1 RC Comment_DataCard2": {},
    "Process1 RC Process_DataCard1": {},
    "Process2 CA Customer Comment_DataCard2": {},
    "Process2 CA Customer Control Item_DataCard1": {},
    "Process2 CA Customer Implementation Date_DataCard1": {},
    "Process2 CA Customer Spec/Control_DataCard1": {},
    "Process2 CA Internal Comment_DataCard2": {},
    "Process2 CA Internal Control Item_DataCard1": {},
    "Process2 CA Internal Equipment Improvement_DataCard1": {},
    "Process2 CA Internal Implementation Date_DataCard1": {},
    "Process2 CA Internal Spec/Control_DataCard1": {},
    "Process2 RC Actual Cause_DataCard1": {},
    "Process2 RC Comment_DataCard2": {},
    "Process2 RC Process_DataCard1": {},
    "Process3 CA Customer Comment_DataCard2": {},
    "Process3 CA Customer Control Item_DataCard1": {},
    "Process3 CA Customer Implementation Date_DataCard1": {},
    "Process3 CA Customer Spec/Control_DataCard1": {},
    "Process3 CA Internal Comment_DataCard2": {},
    "Process3 CA Internal Control Item_DataCard1": {},
    "Process3 CA Internal Equipment Improvement_DataCard1": {},
    "Process3 CA Internal Implementation Date_DataCard1": {},
    "Process3 CA Internal Spec/Control_DataCard1": {},
    "Process3 RC Actual Cause_DataCard1": {},
    "Process3 RC Comment_DataCard2": {},
    "Process3 RC Process_DataCard1": {},
    "rdbClaimDescriptionType": {},
    "Rectangle_Header": {},
    "Rectangle11": {},
    "Rectangle2": {},
    "RectQuickActionBar1": {},
    "Screen1": {},
    "scrQPS": {},
    "SearchIcon1": {},
    "Separator2": {},
    "SharePointIntegration": {},
    "Site_DataCard1": {},
    "StarVisible1": {},
    "StarVisible10": {},
    "StarVisible11": {},
    "StarVisible12": {},
    "StarVisible13": {},
    "StarVisible14": {},
    "StarVisible15": {},
    "StarVisible16": {},
    "StarVisible17": {},
    "StarVisible18": {},
    "StarVisible19": {},
    "StarVisible2": {},
    "StarVisible20": {},
    "StarVisible21": {},
    "StarVisible22": {},
    "StarVisible23": {},
    "StarVisible24": {},
    "StarVisible25": {},
    "StarVisible26": {},
    "StarVisible27": {},
    "StarVisible28": {},
    "StarVisible29": {},
    "StarVisible3": {},
    "StarVisible30": {},
    "StarVisible31": {},
    "StarVisible32": {},
    "StarVisible33": {},
    "StarVisible34": {},
    "StarVisible35": {},
    "StarVisible36": {},
    "StarVisible37": {},
    "StarVisible38": {},
    "StarVisible39": {},
    "StarVisible40": {},
    "StarVisible41": {},
    "StarVisible42": {},
    "StarVisible43": {},
    "StarVisible44": {},
    "StarVisible45": {},
    "StarVisible46": {},
    "StarVisible47": {},
    "StarVisible48": {},
    "StarVisible49": {},
    "StarVisible5": {},
    "StarVisible50": {},
    "StarVisible51": {},
    "StarVisible52": {},
    "StarVisible54": {},
    "StarVisible55": {},
    "StarVisible6": {},
    "StarVisible7": {},
    "StarVisible8": {},
    "StarVisible9": {},
    "Status_DataCard1": {},
    "Substrate Program_DataCard1": {},
    "Substrate Supplier_DataCard1": {},
    "Subtitle2": {},
    "TextSearchBox1": {},
    "Title2": {},
    "イメージ_DataCard1": {},
    "タイトル_DataCard1": {},
    "備考_DataCard2": {}
  },
  "PCFDynamicSchemaForIRRetrievalEntry": {},
  "PCFTemplateEntry": {},
  "PublishOrderIndices": {
    "AddPicture1": 254,
    "App": 0,
    "Applied Program Comment_DataCard2": 237,
    "Applied Program_DataCard1": 232,
    "Body1": 313,
    "BrowseGallery1": 306,
    "btnProcess": 5,
    "Claim description type_DataCard1": 273,
    "Claim description_DataCard1": 268,
    "cmbClaimDescription": 303,
    "cmbMediaProgram": 39,
    "cmbMediaProgram_1": 50,
    "cmbSubstrateProgram": 44,
    "Comment_DataCard1": 24,
    "Customer_DataCard1": 278,
    "DataCard1": 18,
    "DataCard2": 35,
    "DataCard3": 40,
    "DataCard4": 45,
    "DataCardKey1": 11,
    "DataCardKey10": 281,
    "DataCardKey10_1": 36,
    "DataCardKey11": 286,
    "DataCardKey11_1": 38,
    "DataCardKey12": 291,
    "DataCardKey12_1": 41,
    "DataCardKey13": 296,
    "DataCardKey13_1": 43,
    "DataCardKey14": 55,
    "DataCardKey14_1": 51,
    "DataCardKey15": 60,
    "DataCardKey16": 80,
    "DataCardKey17": 70,
    "DataCardKey18": 75,
    "DataCardKey19": 125,
    "DataCardKey2": 32,
    "DataCardKey20": 84,
    "DataCardKey21": 90,
    "DataCardKey22": 95,
    "DataCardKey23": 100,
    "DataCardKey24": 105,
    "DataCardKey25": 110,
    "DataCardKey26": 115,
    "DataCardKey27": 120,
    "DataCardKey28": 140,
    "DataCardKey29": 130,
    "DataCardKey3": 15,
    "DataCardKey30": 135,
    "DataCardKey31": 165,
    "DataCardKey32": 144,
    "DataCardKey33": 150,
    "DataCardKey34": 155,
    "DataCardKey35": 160,
    "DataCardKey36": 185,
    "DataCardKey37": 170,
    "DataCardKey38": 175,
    "DataCardKey39": 180,
    "DataCardKey40": 200,
    "DataCardKey41": 190,
    "DataCardKey42": 195,
    "DataCardKey43": 225,
    "DataCardKey44": 204,
    "DataCardKey45": 210,
    "DataCardKey46": 215,
    "DataCardKey47": 220,
    "DataCardKey48": 240,
    "DataCardKey49": 230,
    "DataCardKey5": 266,
    "DataCardKey5_1": 23,
    "DataCardKey50": 235,
    "DataCardKey51": 250,
    "DataCardKey52": 245,
    "DataCardKey54": 256,
    "DataCardKey55": 261,
    "DataCardKey6": 65,
    "DataCardKey7": 276,
    "DataCardKey7_1": 20,
    "DataCardKey8": 271,
    "DataCardKey9": 27,
    "DataCardValue1": 9,
    "DataCardValue10": 279,
    "DataCardValue11": 284,
    "DataCardValue12": 289,
    "DataCardValue13": 294,
    "DataCardValue14": 53,
    "DataCardValue15": 58,
    "DataCardValue16": 78,
    "DataCardValue17": 68,
    "DataCardValue18": 73,
    "DataCardValue19": 123,
    "DataCardValue2": 33,
    "DataCardValue20": 85,
    "DataCardValue21": 88,
    "DataCardValue22": 93,
    "DataCardValue23": 98,
    "DataCardValue24": 103,
    "DataCardValue25": 108,
    "DataCardValue26": 113,
    "DataCardValue27": 118,
    "DataCardValue28": 138,
    "DataCardValue29": 128,
    "DataCardValue3": 16,
    "DataCardValue30": 133,
    "DataCardValue31": 163,
    "DataCardValue32": 145,
    "DataCardValue33": 148,
    "DataCardValue34": 153,
    "DataCardValue35": 158,
    "DataCardValue36": 183,
    "DataCardValue37": 168,
    "DataCardValue38": 173,
    "DataCardValue39": 178,
    "DataCardValue40": 198,
    "DataCardValue41": 188,
    "DataCardValue42": 193,
    "DataCardValue43": 223,
    "DataCardValue44": 205,
    "DataCardValue45": 208,
    "DataCardValue46": 213,
    "DataCardValue47": 218,
    "DataCardValue48": 238,
    "DataCardValue49": 228,
    "DataCardValue5": 264,
    "DataCardValue50": 233,
    "DataCardValue51": 248,
    "DataCardValue52": 243,
    "DataCardValue54": 259,
    "DataCardValue6": 63,
    "DataCardValue7": 274,
    "DataCardValue8": 269,
    "DataCardValue9": 25,
    "Date_DataCard1": 13,
    "ddlClaimDescription": 22,
    "ddlCustomer": 37,
    "ddlP1RCProcess": 48,
    "ddlSite": 19,
    "ddlSubstrateSupplier": 42,
    "Edit History_DataCard1": 258,
    "Equip_DataCard1": 242,
    "ErrorMessage1": 12,
    "ErrorMessage10": 282,
    "ErrorMessage11": 287,
    "ErrorMessage12": 292,
    "ErrorMessage13": 297,
    "ErrorMessage14": 56,
    "ErrorMessage15": 61,
    "ErrorMessage16": 81,
    "ErrorMessage17": 71,
    "ErrorMessage18": 76,
    "ErrorMessage19": 126,
    "ErrorMessage2": 34,
    "ErrorMessage20": 86,
    "ErrorMessage21": 91,
    "ErrorMessage22": 96,
    "ErrorMessage23": 101,
    "ErrorMessage24": 106,
    "ErrorMessage25": 111,
    "ErrorMessage26": 116,
    "ErrorMessage27": 121,
    "ErrorMessage28": 141,
    "ErrorMessage29": 131,
    "ErrorMessage3": 17,
    "ErrorMessage30": 136,
    "ErrorMessage31": 166,
    "ErrorMessage32": 146,
    "ErrorMessage33": 151,
    "ErrorMessage34": 156,
    "ErrorMessage35": 161,
    "ErrorMessage36": 186,
    "ErrorMessage37": 171,
    "ErrorMessage38": 176,
    "ErrorMessage39": 181,
    "ErrorMessage40": 201,
    "ErrorMessage41": 191,
    "ErrorMessage42": 196,
    "ErrorMessage43": 226,
    "ErrorMessage44": 206,
    "ErrorMessage45": 211,
    "ErrorMessage46": 216,
    "ErrorMessage47": 221,
    "ErrorMessage48": 241,
    "ErrorMessage49": 231,
    "ErrorMessage5": 267,
    "ErrorMessage50": 236,
    "ErrorMessage51": 251,
    "ErrorMessage52": 246,
    "ErrorMessage54": 257,
    "ErrorMessage55": 262,
    "ErrorMessage6": 66,
    "ErrorMessage7": 277,
    "ErrorMessage8": 272,
    "ErrorMessage9": 28,
    "ErrorMessage9_1": 29,
    "frmQPS": 6,
    "galleryTemplate1": 307,
    "galleryTemplate2": 4,
    "galProcess": 3,
    "Host": 0,
    "IconNewItem1": 301,
    "IconRefresh1": 299,
    "IconSortUpDown1": 300,
    "Image1": 253,
    "Image3": 309,
    "Label1": 8,
    "lbl_Header": 1,
    "LblAppName1": 302,
    "lblP1RCActualCause": 49,
    "lblProcess1": 47,
    "lblRootcause": 46,
    "lblStatus": 2,
    "Media Program_DataCard1": 283,
    "NextArrow2": 311,
    "Process1 CA Customer Comment_DataCard1": 107,
    "Process1 CA Customer Control Item_DataCard1": 92,
    "Process1 CA Customer Implementation Date_DataCard1": 97,
    "Process1 CA Customer Spec/Control_DataCard1": 102,
    "Process1 CA Internal Comment_DataCard2": 77,
    "Process1 CA Internal Control Item_DataCard1": 67,
    "Process1 CA Internal Equipment Improvement_DataCard1": 82,
    "Process1 CA Internal Implementation Date_DataCard1": 87,
    "Process1 CA Internal Spec/Control_DataCard1": 72,
    "Process1 RC Actual Cause_DataCard1": 57,
    "Process1 RC Comment_DataCard2": 62,
    "Process1 RC Process_DataCard1": 52,
    "Process2 CA Customer Comment_DataCard2": 162,
    "Process2 CA Customer Control Item_DataCard1": 152,
    "Process2 CA Customer Implementation Date_DataCard1": 167,
    "Process2 CA Customer Spec/Control_DataCard1": 157,
    "Process2 CA Internal Comment_DataCard2": 137,
    "Process2 CA Internal Control Item_DataCard1": 127,
    "Process2 CA Internal Equipment Improvement_DataCard1": 142,
    "Process2 CA Internal Implementation Date_DataCard1": 147,
    "Process2 CA Internal Spec/Control_DataCard1": 132,
    "Process2 RC Actual Cause_DataCard1": 117,
    "Process2 RC Comment_DataCard2": 122,
    "Process2 RC Process_DataCard1": 112,
    "Process3 CA Customer Comment_DataCard2": 222,
    "Process3 CA Customer Control Item_DataCard1": 212,
    "Process3 CA Customer Implementation Date_DataCard1": 227,
    "Process3 CA Customer Spec/Control_DataCard1": 217,
    "Process3 CA Internal Comment_DataCard2": 197,
    "Process3 CA Internal Control Item_DataCard1": 187,
    "Process3 CA Internal Equipment Improvement_DataCard1": 202,
    "Process3 CA Internal Implementation Date_DataCard1": 207,
    "Process3 CA Internal Spec/Control_DataCard1": 192,
    "Process3 RC Actual Cause_DataCard1": 177,
    "Process3 RC Comment_DataCard2": 182,
    "Process3 RC Process_DataCard1": 172,
    "rdbClaimDescriptionType": 21,
    "Rectangle_Header": 0,
    "Rectangle11": 315,
    "Rectangle2": 308,
    "RectQuickActionBar1": 298,
    "Screen1": 0,
    "scrQPS": 0,
    "SearchIcon1": 305,
    "Separator2": 314,
    "SharePointIntegration": 0,
    "Site_DataCard1": 263,
    "StarVisible1": 10,
    "StarVisible10": 280,
    "StarVisible11": 285,
    "StarVisible12": 290,
    "StarVisible13": 295,
    "StarVisible14": 54,
    "StarVisible15": 59,
    "StarVisible16": 79,
    "StarVisible17": 69,
    "StarVisible18": 74,
    "StarVisible19": 124,
    "StarVisible2": 31,
    "StarVisible20": 83,
    "StarVisible21": 89,
    "StarVisible22": 94,
    "StarVisible23": 99,
    "StarVisible24": 104,
    "StarVisible25": 109,
    "StarVisible26": 114,
    "StarVisible27": 119,
    "StarVisible28": 139,
    "StarVisible29": 129,
    "StarVisible3": 14,
    "StarVisible30": 134,
    "StarVisible31": 164,
    "StarVisible32": 143,
    "StarVisible33": 149,
    "StarVisible34": 154,
    "StarVisible35": 159,
    "StarVisible36": 184,
    "StarVisible37": 169,
    "StarVisible38": 174,
    "StarVisible39": 179,
    "StarVisible40": 199,
    "StarVisible41": 189,
    "StarVisible42": 194,
    "StarVisible43": 224,
    "StarVisible44": 203,
    "StarVisible45": 209,
    "StarVisible46": 214,
    "StarVisible47": 219,
    "StarVisible48": 239,
    "StarVisible49": 229,
    "StarVisible5": 265,
    "StarVisible50": 234,
    "StarVisible51": 249,
    "StarVisible52": 244,
    "StarVisible54": 255,
    "StarVisible55": 260,
    "StarVisible6": 64,
    "StarVisible7": 275,
    "StarVisible8": 270,
    "StarVisible9": 26,
    "Status_DataCard1": 30,
    "Substrate Program_DataCard1": 293,
    "Substrate Supplier_DataCard1": 288,
    "Subtitle2": 312,
    "TextSearchBox1": 304,
    "Title2": 310,
    "イメージ_DataCard1": 252,
    "タイトル_DataCard1": 7,
    "備考_DataCard2": 247
  },
  "ResourcesJsonIndices": {
    "Image-SampleImage": 0
  },
  "RuleScreenIdWithoutScreen": {},
  "TemplateVersions": {},
  "VolatileProperties": {
    "AnalysisLoadTime": 9.1379498,
    "ControlCount": {
      "addMedia": 1,
      "button": 1,
      "combobox": 6,
      "datepicker": 7,
      "dropdown": 5,
      "form": 1,
      "gallery": 2,
      "galleryTemplate": 2,
      "hostControl": 1,
      "icon": 5,
      "image": 2,
      "label": 177,
      "radio": 1,
      "rectangle": 5,
      "richTextEditor": 10,
      "screen": 2,
      "text": 31,
      "toggleSwitch": 3,
      "typedDataCard": 57
    },
    "DeserializationLoadTime": 9.8229918
  },
  "WasLocalDatabaseReferencesEmpty": true
}